{
  "assignee": "",
  "blocked_by": [],
  "blocks": [],
  "created": "",
  "description": "Harrison Ford/Amy Adams/KT Tunstall. late_night, S13E80, 2006.\nRuntime: 57 min.\nIMDb: https://www.imdb.com/title/tt0627791/\n_search: Harrison Ford/Amy Adams/KT Tunstall | 2006 | S13E80",
  "id": "bw-e-tt0627791",
  "labels": [
    "kind:episode",
    "era:late_night",
    "source:imdb_seed",
    "privacy:public_record"
  ],
  "priority": 2,
  "status": "open",
  "title": "Harrison Ford/Amy Adams/KT Tunstall",
  "type": "task"
}
