{
  "assignee": "",
  "blocked_by": [],
  "blocks": [],
  "created": "",
  "description": "Jason Priestley/Stockard Channing/Maria Bamford. late_night, S7E69, 2000.\nRuntime: 57 min.\nIMDb: https://www.imdb.com/title/tt0627323/\n_search: Jason Priestley/Stockard Channing/Maria Bamford | 2000 | S7E69",
  "id": "bw-e-tt0627323",
  "labels": [
    "kind:episode",
    "era:late_night",
    "source:imdb_seed",
    "privacy:public_record"
  ],
  "priority": 2,
  "status": "open",
  "title": "Jason Priestley/Stockard Channing/Maria Bamford",
  "type": "task"
}
