{
  "assignee": "",
  "blocked_by": [],
  "blocks": [],
  "created": "",
  "description": "Tom Brokaw/Marc Maron/Soggy Bottom Boys. late_night, S8E128, 2001.\nRuntime: 57 min.\nIMDb: https://www.imdb.com/title/tt3823956/\n_search: Tom Brokaw/Marc Maron/Soggy Bottom Boys | 2001 | S8E128",
  "id": "bw-e-tt3823956",
  "labels": [
    "kind:episode",
    "era:late_night",
    "source:imdb_seed",
    "privacy:public_record"
  ],
  "priority": 2,
  "status": "open",
  "title": "Tom Brokaw/Marc Maron/Soggy Bottom Boys",
  "type": "task"
}
