{
  "assignee": "",
  "blocked_by": [],
  "blocks": [],
  "created": "",
  "description": "Renée Zellweger/Chris Titus/James Lipton. late_night, S8E98, 2001.\nRuntime: 57 min.\nIMDb: https://www.imdb.com/title/tt2898466/\n_search: Renée Zellweger/Chris Titus/James Lipton | 2001 | S8E98",
  "id": "bw-e-tt2898466",
  "labels": [
    "kind:episode",
    "era:late_night",
    "source:imdb_seed",
    "privacy:public_record"
  ],
  "priority": 2,
  "status": "open",
  "title": "Renée Zellweger/Chris Titus/James Lipton",
  "type": "task"
}
