{
  "assignee": "",
  "blocked_by": [],
  "blocks": [],
  "created": "",
  "description": "Elijah Wood/Rachel Dratch/B.J. Novak. late_night, S11E84, 2004.\nRuntime: 57 min.\nIMDb rating: 6.6.\nIMDb: https://www.imdb.com/title/tt0627519/\n_search: Elijah Wood/Rachel Dratch/B.J. Novak | 2004 | S11E84",
  "id": "bw-e-tt0627519",
  "labels": [
    "kind:episode",
    "era:late_night",
    "source:imdb_seed",
    "privacy:public_record"
  ],
  "priority": 2,
  "status": "open",
  "title": "Elijah Wood/Rachel Dratch/B.J. Novak",
  "type": "task"
}
