{
  "assignee": "",
  "blocked_by": [],
  "blocks": [],
  "created": "",
  "description": "Seven Salads for Seven Brothers Who Are Sexually Attracted to Salads. conan_tbs, S1E62, 2011.\nRuntime: 60 min.\nIMDb rating: 8.5.\nIMDb: https://www.imdb.com/title/tt1853912/\n_search: Seven Salads for Seven Brothers Who Are Sexually Attracted to Salads | 2011 | S1E62",
  "id": "bw-e-tt1853912",
  "labels": [
    "kind:episode",
    "era:conan_tbs",
    "source:imdb_seed",
    "privacy:public_record"
  ],
  "priority": 2,
  "status": "open",
  "title": "Seven Salads for Seven Brothers Who Are Sexually Attracted to Salads",
  "type": "task"
}
