{
  "assignee": "",
  "blocked_by": [],
  "blocks": [],
  "created": "",
  "description": "Bob Saget/Maggie Q/Shane Mauss. late_night, S14E182, 2007.\nRuntime: 57 min.\nIMDb: https://www.imdb.com/title/tt1090487/\n_search: Bob Saget/Maggie Q/Shane Mauss | 2007 | S14E182",
  "id": "bw-e-tt1090487",
  "labels": [
    "kind:episode",
    "era:late_night",
    "source:imdb_seed",
    "privacy:public_record"
  ],
  "priority": 2,
  "status": "open",
  "title": "Bob Saget/Maggie Q/Shane Mauss",
  "type": "task"
}
