{
  "assignee": "",
  "blocked_by": [],
  "blocks": [],
  "created": "",
  "description": "Chris Rock/Shannon Elizabeth/Joe Buck. late_night, S11E100, 2004.\nRuntime: 57 min.\nIMDb: https://www.imdb.com/title/tt0627530/\n_search: Chris Rock/Shannon Elizabeth/Joe Buck | 2004 | S11E100",
  "id": "bw-e-tt0627530",
  "labels": [
    "kind:episode",
    "era:late_night",
    "source:imdb_seed",
    "privacy:public_record"
  ],
  "priority": 2,
  "status": "open",
  "title": "Chris Rock/Shannon Elizabeth/Joe Buck",
  "type": "task"
}
