{
  "assignee": "",
  "blocked_by": [],
  "blocks": [],
  "created": "",
  "description": "Tracy Morgan/Chris Hansen/Paul Thorn. late_night, S15E84, 2008.\nRuntime: 57 min.\nIMDb: https://www.imdb.com/title/tt12099820/\n_search: Tracy Morgan/Chris Hansen/Paul Thorn | 2008 | S15E84",
  "id": "bw-e-tt12099820",
  "labels": [
    "kind:episode",
    "era:late_night",
    "source:imdb_seed",
    "privacy:public_record"
  ],
  "priority": 2,
  "status": "open",
  "title": "Tracy Morgan/Chris Hansen/Paul Thorn",
  "type": "task"
}
