{
  "assignee": "",
  "blocked_by": [],
  "blocks": [],
  "created": "",
  "description": "Jeffrey Tambor/Harry Connick Jr.. late_night, S6E149, 1999.\nRuntime: 57 min.\nIMDb: https://www.imdb.com/title/tt4258936/\n_search: Jeffrey Tambor/Harry Connick Jr. | 1999 | S6E149",
  "id": "bw-e-tt4258936",
  "labels": [
    "kind:episode",
    "era:late_night",
    "source:imdb_seed",
    "privacy:public_record"
  ],
  "priority": 2,
  "status": "open",
  "title": "Jeffrey Tambor/Harry Connick Jr.",
  "type": "task"
}
