{
  "assignee": "",
  "blocked_by": [],
  "blocks": [],
  "created": "",
  "description": "Jeff Goldblum/Omarosa Stallworth/Sarah McLachlan. late_night, S11E83, 2004.\nRuntime: 57 min.\nIMDb: https://www.imdb.com/title/tt0883749/\n_search: Jeff Goldblum/Omarosa Stallworth/Sarah McLachlan | 2004 | S11E83",
  "id": "bw-e-tt0883749",
  "labels": [
    "kind:episode",
    "era:late_night",
    "source:imdb_seed",
    "privacy:public_record"
  ],
  "priority": 2,
  "status": "open",
  "title": "Jeff Goldblum/Omarosa Stallworth/Sarah McLachlan",
  "type": "task"
}
