{
  "assignee": "",
  "blocked_by": [],
  "blocks": [],
  "created": "",
  "description": "Jim Carrey/Olivia Wilde/Zac Brown Band. tonight_show, S1E97, 2009.\nIMDb rating: 6.2.\nIMDb: https://www.imdb.com/title/tt1538193/\n_search: Jim Carrey/Olivia Wilde/Zac Brown Band | 2009 | S1E97",
  "id": "bw-e-tt1538193",
  "labels": [
    "kind:episode",
    "era:tonight_show",
    "source:imdb_seed",
    "privacy:public_record"
  ],
  "priority": 2,
  "status": "open",
  "title": "Jim Carrey/Olivia Wilde/Zac Brown Band",
  "type": "task"
}
