{
  "assignee": "",
  "blocked_by": [],
  "blocks": [],
  "created": "",
  "description": "Ryan Reynolds/Matt Lauer/Simple Plan. late_night, S15E64, 2008.\nRuntime: 57 min.\nIMDb: https://www.imdb.com/title/tt1225486/\n_search: Ryan Reynolds/Matt Lauer/Simple Plan | 2008 | S15E64",
  "id": "bw-e-tt1225486",
  "labels": [
    "kind:episode",
    "era:late_night",
    "source:imdb_seed",
    "privacy:public_record"
  ],
  "priority": 2,
  "status": "open",
  "title": "Ryan Reynolds/Matt Lauer/Simple Plan",
  "type": "task"
}
