{
  "assignee": "",
  "blocked_by": [],
  "blocks": [],
  "created": "",
  "description": "Jennifer Connelly/Zane Lamprey/Ziggy Marley. tonight_show, S1E60, 2009.\nIMDb rating: 7.3.\nIMDb: https://www.imdb.com/title/tt1504835/\n_search: Jennifer Connelly/Zane Lamprey/Ziggy Marley | 2009 | S1E60",
  "id": "bw-e-tt1504835",
  "labels": [
    "kind:episode",
    "era:tonight_show",
    "source:imdb_seed",
    "privacy:public_record"
  ],
  "priority": 2,
  "status": "open",
  "title": "Jennifer Connelly/Zane Lamprey/Ziggy Marley",
  "type": "task"
}
