{
  "assignee": "",
  "blocked_by": [],
  "blocks": [],
  "created": "",
  "description": "Thane Maynard/Dweezil \u0026 Ahmet Zappa/Greg Behrendt. late_night, S6E94, 1999.\nRuntime: 57 min.\nIMDb: https://www.imdb.com/title/tt0627222/\n_search: Thane Maynard/Dweezil \u0026 Ahmet Zappa/Greg Behrendt | 1999 | S6E94",
  "id": "bw-e-tt0627222",
  "labels": [
    "kind:episode",
    "era:late_night",
    "source:imdb_seed",
    "privacy:public_record"
  ],
  "priority": 2,
  "status": "open",
  "title": "Thane Maynard/Dweezil \u0026 Ahmet Zappa/Greg Behrendt",
  "type": "task"
}
