{
  "assignee": "",
  "blocked_by": [],
  "blocks": [],
  "created": "",
  "description": "James Brown/Jonathan Taylor Thomas. late_night, S4E134, 1997.\nRuntime: 57 min.\nIMDb: https://www.imdb.com/title/tt3769500/\n_search: James Brown/Jonathan Taylor Thomas | 1997 | S4E134",
  "id": "bw-e-tt3769500",
  "labels": [
    "kind:episode",
    "era:late_night",
    "source:imdb_seed",
    "privacy:public_record"
  ],
  "priority": 2,
  "status": "open",
  "title": "James Brown/Jonathan Taylor Thomas",
  "type": "task"
}
