{
  "assignee": "",
  "blocked_by": [],
  "blocks": [],
  "created": "",
  "description": "Kelsey Grammer/Mariska Hargitay/Lewis Black. late_night, S11E111, 2004.\nRuntime: 57 min.\nIMDb: https://www.imdb.com/title/tt0627539/\n_search: Kelsey Grammer/Mariska Hargitay/Lewis Black | 2004 | S11E111",
  "id": "bw-e-tt0627539",
  "labels": [
    "kind:episode",
    "era:late_night",
    "source:imdb_seed",
    "privacy:public_record"
  ],
  "priority": 2,
  "status": "open",
  "title": "Kelsey Grammer/Mariska Hargitay/Lewis Black",
  "type": "task"
}
