{
  "assignee": "",
  "blocked_by": [],
  "blocks": [],
  "created": "",
  "description": "Did Somebody Order an Extendre with Extra Penis?. conan_tbs, S4E34, 2014.\nIMDb: https://www.imdb.com/title/tt3482206/\n_search: Did Somebody Order an Extendre with Extra Penis? | 2014 | S4E34",
  "id": "bw-e-tt3482206",
  "labels": [
    "kind:episode",
    "era:conan_tbs",
    "source:imdb_seed",
    "privacy:public_record"
  ],
  "priority": 2,
  "status": "open",
  "title": "Did Somebody Order an Extendre with Extra Penis?",
  "type": "task"
}
