{
  "assignee": "",
  "blocked_by": [],
  "blocks": [],
  "created": "",
  "description": "Richard Lewis/Tabitha Soren/Steve and Leo. late_night, S3E53, 1995.\nRuntime: 57 min.\nIMDb: https://www.imdb.com/title/tt3408238/\n_search: Richard Lewis/Tabitha Soren/Steve and Leo | 1995 | S3E53",
  "id": "bw-e-tt3408238",
  "labels": [
    "kind:episode",
    "era:late_night",
    "source:imdb_seed",
    "privacy:public_record"
  ],
  "priority": 2,
  "status": "open",
  "title": "Richard Lewis/Tabitha Soren/Steve and Leo",
  "type": "task"
}
