{
  "assignee": "",
  "blocked_by": [],
  "blocks": [],
  "created": "",
  "description": "Chris Botti. b. 1962 | music_artist, music_department, actor.\nConan-show appearances: 0\nIMDb: https://www.imdb.com/name/nm0098660/\n_search: Chris Botti | The Bucket List | August Rush | Caught | Playing by Heart",
  "id": "bw-p-nm0098660",
  "labels": [
    "kind:person",
    "source:imdb_seed",
    "era:late_night",
    "privacy:public_record"
  ],
  "priority": 2,
  "status": "open",
  "title": "Chris Botti",
  "type": "task"
}
