{
  "assignee": "",
  "blocked_by": [],
  "blocks": [],
  "created": "",
  "description": "Randy Quaid. b. 1950 | actor, producer, writer.\nConan-show appearances: 1\nIMDb: https://www.imdb.com/name/nm0001642/\n_search: Randy Quaid | Kingpin | Independence Day | National Lampoon's Christmas Vacation | National Lampoon's Vacation",
  "id": "bw-p-nm0001642",
  "labels": [
    "kind:person",
    "source:imdb_seed",
    "era:late_night",
    "privacy:public_record"
  ],
  "priority": 2,
  "status": "open",
  "title": "Randy Quaid",
  "type": "task"
}
