{
  "assignee": "",
  "blocked_by": [],
  "blocks": [],
  "created": "",
  "description": "Forrest Shaw. producer, writer, actor.\nConan-show appearances: 1\nIMDb: https://www.imdb.com/name/nm5248959/\n_search: Forrest Shaw | Labor Days | Better Off with Hally Leadbetter | The Conor Moore Show | Golf Road Trippin with James Davis",
  "id": "bw-p-nm5248959",
  "labels": [
    "kind:person",
    "source:imdb_seed",
    "era:conan_tbs",
    "privacy:public_record"
  ],
  "priority": 2,
  "status": "open",
  "title": "Forrest Shaw",
  "type": "task"
}
