{
  "assignee": "",
  "blocked_by": [],
  "blocks": [],
  "created": "",
  "description": "Elle Fanning. b. 1998 | actress, producer, director.\nConan-show appearances: 3\nIMDb: https://www.imdb.com/name/nm1102577/\n_search: Elle Fanning | Super 8 | Predator: Badlands | The Neon Demon | Somewhere",
  "id": "bw-p-nm1102577",
  "labels": [
    "kind:person",
    "source:imdb_seed",
    "era:conan_tbs",
    "privacy:public_record"
  ],
  "priority": 2,
  "status": "open",
  "title": "Elle Fanning",
  "type": "task"
}
