{
  "assignee": "",
  "blocked_by": [],
  "blocks": [],
  "created": "",
  "description": "Stanley Tucci. b. 1960 | actor, producer, writer.\nConan-show appearances: 2\nIMDb: https://www.imdb.com/name/nm0001804/\n_search: Stanley Tucci | Big Night | Spotlight | The Lovely Bones | Captain America: The First Avenger",
  "id": "bw-p-nm0001804",
  "labels": [
    "kind:person",
    "source:imdb_seed",
    "era:late_night",
    "privacy:public_record"
  ],
  "priority": 2,
  "status": "open",
  "title": "Stanley Tucci",
  "type": "task"
}
