{
  "assignee": "",
  "blocked_by": [],
  "blocks": [],
  "created": "",
  "description": "Rob Zabrecky. b. 1968 | actor, producer, writer.\nConan-show appearances: 0\nIMDb: https://www.imdb.com/name/nm1884657/\n_search: Rob Zabrecky | A Ghost Story | Lost River | Criminal Minds | Decay",
  "id": "bw-p-nm1884657",
  "labels": [
    "kind:person",
    "source:imdb_seed",
    "era:late_night",
    "privacy:public_record"
  ],
  "priority": 2,
  "status": "open",
  "title": "Rob Zabrecky",
  "type": "task"
}
