{
  "assignee": "",
  "blocked_by": [],
  "blocks": [],
  "created": "",
  "description": "Donna Murphy. actress, soundtrack, archive_footage.\nConan-show appearances: 0\nIMDb: https://www.imdb.com/name/nm0614220/\n_search: Donna Murphy | The Gilded Age | Brilliant Minds | Tangled | Center Stage",
  "id": "bw-p-nm0614220",
  "labels": [
    "kind:person",
    "source:imdb_seed",
    "era:late_night",
    "privacy:public_record"
  ],
  "priority": 2,
  "status": "open",
  "title": "Donna Murphy",
  "type": "task"
}
