{
  "assignee": "",
  "blocked_by": [],
  "blocks": [],
  "created": "",
  "description": "John Daly. b. 1966 | actor, archive_footage.\nConan-show appearances: 1\nIMDb: https://www.imdb.com/name/nm1503649/\n_search: John Daly | Happy Gilmore 2 | NWA: Total Nonstop Action | NFL Monday Night Football | The 'Vous",
  "id": "bw-p-nm1503649",
  "labels": [
    "kind:person",
    "source:imdb_seed",
    "era:late_night",
    "privacy:public_record"
  ],
  "priority": 2,
  "status": "open",
  "title": "John Daly",
  "type": "task"
}
