{
  "assignee": "",
  "blocked_by": [],
  "blocks": [],
  "created": "",
  "description": "Chaz Bono. b. 1969 | actor, producer, miscellaneous.\nConan-show appearances: 1\nIMDb: https://www.imdb.com/name/nm0095106/\n_search: Chaz Bono | American Horror Story | Curb Your Enthusiasm | The Bold and the Beautiful | Reboot Camp",
  "id": "bw-p-nm0095106",
  "labels": [
    "kind:person",
    "source:imdb_seed",
    "era:late_night",
    "privacy:public_record"
  ],
  "priority": 2,
  "status": "open",
  "title": "Chaz Bono",
  "type": "task"
}
