{
  "assignee": "",
  "blocked_by": [],
  "blocks": [],
  "created": "",
  "description": "Tony Meola. b. 1969 | actor, archive_footage.\nConan-show appearances: 1\nIMDb: https://www.imdb.com/name/nm1155874/\n_search: Tony Meola | Zigs | The Billion Dollar Goal | What'Cha Got | Summer of 94",
  "id": "bw-p-nm1155874",
  "labels": [
    "kind:person",
    "source:imdb_seed",
    "era:late_night",
    "privacy:public_record"
  ],
  "priority": 2,
  "status": "open",
  "title": "Tony Meola",
  "type": "task"
}
