{
  "assignee": "",
  "blocked_by": [],
  "blocks": [],
  "created": "",
  "description": "Nikiya Palombi. actress, producer, choreographer.\nConan-show appearances: 0\nIMDb: https://www.imdb.com/name/nm3263960/\n_search: Nikiya Palombi | Gunner Jackson | My Holographic Heart | Dancer",
  "id": "bw-p-nm3263960",
  "labels": [
    "kind:person",
    "source:imdb_seed",
    "era:conan_tbs",
    "privacy:public_record"
  ],
  "priority": 2,
  "status": "open",
  "title": "Nikiya Palombi",
  "type": "task"
}
