{
  "assignee": "",
  "blocked_by": [],
  "blocks": [],
  "created": "",
  "description": "Deborah Norville. b. 1958 | producer, actress, writer.\nConan-show appearances: 4\nIMDb: https://www.imdb.com/name/nm0636354/\n_search: Deborah Norville | The Game | The Young and the Restless | Deborah Norville Tonight | Inside Edition",
  "id": "bw-p-nm0636354",
  "labels": [
    "kind:person",
    "source:imdb_seed",
    "era:late_night",
    "privacy:public_record"
  ],
  "priority": 2,
  "status": "open",
  "title": "Deborah Norville",
  "type": "task"
}
