{
  "assignee": "",
  "blocked_by": [],
  "blocks": [],
  "created": "",
  "description": "Keith D. Robinson. b. 1976 | actor, writer, music_department.\nConan-show appearances: 0\nIMDb: https://www.imdb.com/name/nm0732803/\n_search: Keith D. Robinson | Dreamgirls | Dear John | Blade: Trinity | All Eyez on Me",
  "id": "bw-p-nm0732803",
  "labels": [
    "kind:person",
    "source:imdb_seed",
    "era:late_night",
    "privacy:public_record"
  ],
  "priority": 2,
  "status": "open",
  "title": "Keith D. Robinson",
  "type": "task"
}
