{
  "assignee": "",
  "blocked_by": [],
  "blocks": [],
  "created": "",
  "description": "Andy Mrotek. soundtrack.\nConan-show appearances: 0\nIMDb: https://www.imdb.com/name/nm2353442/\n_search: Andy Mrotek | P.S. I Love You | The Hills | Degrassi: The Next Generation | Jimmy Kimmel Live!",
  "id": "bw-p-nm2353442",
  "labels": [
    "kind:person",
    "source:imdb_seed",
    "era:late_night",
    "privacy:public_record"
  ],
  "priority": 2,
  "status": "open",
  "title": "Andy Mrotek",
  "type": "task"
}
