{
  "assignee": "",
  "blocked_by": [],
  "blocks": [],
  "created": "",
  "description": "James Lesure. b. 1970 | actor, soundtrack, archive_footage.\nConan-show appearances: 1\nIMDb: https://www.imdb.com/name/nm0504571/\n_search: James Lesure | Crimson Tide | Las Vegas | Fire with Fire | Men at Work",
  "id": "bw-p-nm0504571",
  "labels": [
    "kind:person",
    "source:imdb_seed",
    "era:conan_tbs",
    "privacy:public_record"
  ],
  "priority": 2,
  "status": "open",
  "title": "James Lesure",
  "type": "task"
}
