{
  "assignee": "",
  "blocked_by": [],
  "blocks": [],
  "created": "",
  "description": "Bill Kreutzmann. b. 1946 | composer, music_department, actor.\nConan-show appearances: 1\nIMDb: https://www.imdb.com/name/nm0471066/\n_search: Bill Kreutzmann | Apocalypse Now | The Dreamers | The Grateful Dead | Flirting with Disaster",
  "id": "bw-p-nm0471066",
  "labels": [
    "kind:person",
    "source:imdb_seed",
    "era:conan_tbs",
    "privacy:public_record"
  ],
  "priority": 2,
  "status": "open",
  "title": "Bill Kreutzmann",
  "type": "task"
}
