{
  "assignee": "",
  "blocked_by": [],
  "blocks": [],
  "created": "",
  "description": "The Marcus King Band. actor, soundtrack.\nConan-show appearances: 0\nIMDb: https://www.imdb.com/name/nm8875855/\n_search: The Marcus King Band | Bloodline | Marcus King: Live in Nashville | CBS Saturday Morning",
  "id": "bw-p-nm8875855",
  "labels": [
    "kind:person",
    "source:imdb_seed",
    "era:conan_tbs",
    "privacy:public_record"
  ],
  "priority": 2,
  "status": "open",
  "title": "The Marcus King Band",
  "type": "task"
}
