{
  "assignee": "",
  "blocked_by": [],
  "blocks": [],
  "created": "",
  "description": "Carl Lewis. b. 1961 | actor, producer, soundtrack.\nConan-show appearances: 0\nIMDb: https://www.imdb.com/name/nm0507006/\n_search: Carl Lewis | Alien Hunter | Rift | Christmas in Compton | Speed Zone",
  "id": "bw-p-nm0507006",
  "labels": [
    "kind:person",
    "source:imdb_seed",
    "era:late_night",
    "privacy:public_record"
  ],
  "priority": 2,
  "status": "open",
  "title": "Carl Lewis",
  "type": "task"
}
