{
  "assignee": "",
  "blocked_by": [],
  "blocks": [],
  "created": "",
  "description": "Jeff Schweikart. b. 1979 | animation_department, editor, director.\nConan-show appearances: 0\nIMDb: https://www.imdb.com/name/nm1204138/\n_search: Jeff Schweikart | The Day After Tomorrow | Hellboy | Dawn of the Dead | Van Helsing",
  "id": "bw-p-nm1204138",
  "labels": [
    "kind:person",
    "source:imdb_seed",
    "era:conan_tbs",
    "privacy:public_record"
  ],
  "priority": 2,
  "status": "open",
  "title": "Jeff Schweikart",
  "type": "task"
}
