{
  "assignee": "",
  "blocked_by": [],
  "blocks": [],
  "created": "",
  "description": "Peter Gabriel. b. 1950 | music_artist, composer, music_department.\nConan-show appearances: 0\nIMDb: https://www.imdb.com/name/nm0300272/\n_search: Peter Gabriel | WALL·E | Rabbit-Proof Fence | Red Planet | Snowden",
  "id": "bw-p-nm0300272",
  "labels": [
    "kind:person",
    "source:imdb_seed",
    "era:late_night",
    "privacy:public_record"
  ],
  "priority": 2,
  "status": "open",
  "title": "Peter Gabriel",
  "type": "task"
}
