{
  "assignee": "",
  "blocked_by": [],
  "blocks": [],
  "created": "",
  "description": "Austin Williams. b. 1996 | actor.\nConan-show appearances: 0\nIMDb: https://www.imdb.com/name/nm2046862/\n_search: Austin Williams | Michael Clayton | One Life to Live | The Girl Next Door | The Good Shepherd",
  "id": "bw-p-nm2046862",
  "labels": [
    "kind:person",
    "source:imdb_seed",
    "era:late_night",
    "privacy:public_record"
  ],
  "priority": 2,
  "status": "open",
  "title": "Austin Williams",
  "type": "task"
}
